{
  "standardUser": {
    "username": "standard_user",
    "password": "secret_sauce"
  },
  "lockedOutUser": {
    "username": "locked_out_user",
    "password": "secret_sauce"
  },
  "problemUser": {
    "username": "problem_user",
    "password": "secret_sauce"
  },
  "performanceUser": {
    "username": "performance_glitch_user",
    "password": "secret_sauce"
  },
  "errorUser": {
    "username": "error_user",
    "password": "secret_sauce"
  },
  "invalidCases": [
    {
      "label": "wrong password",
      "username": "standard_user",
      "password": "wrong_password"
    },
    {
      "label": "empty credentials",
      "username": "",
      "password": ""
    },
    {
      "label": "sql injection attempt",
      "username": "' OR 1=1; --",
      "password": "secret_sauce"
    }
  ]
}